setup.py
SleepAPI/__init__.py
SleepAPI/sleeprespi.py
SleepAPI.egg-info/PKG-INFO
SleepAPI.egg-info/SOURCES.txt
SleepAPI.egg-info/dependency_links.txt
SleepAPI.egg-info/top_level.txt