Metadata-Version: 1.0
Name: SleepAPI
Version: 1.0.0
Summary: SLEEP AND RESPI RESULT
Home-page: UNKNOWN
Author: ZZX-NJUST
Author-email: UNKNOWN
License: UNKNOWN
Platform: UNKNOWN
